[
    {
        "invoice_number": "",
        "date": "23/07/2025",
        "company": "",
        "amount": "",
        "items": [
            {
                "description": "Excl. GST",
                "quantity": null,
                "unit_price": null,
                "amount": null
            },
            {
                "description": "CO coraptus",
                "quantity": null,
                "unit_price": null,
                "amount": null
            },
            {
                "description": "Coraplus India Private Limited",
                "quantity": null,
                "unit_price": null,
                "amount": null
            },
            {
                "description": "Plot No. A-",
                "quantity": null,
                "unit_price": null,
                "amount": null
            },
            {
                "description": "Wagle Industrial Estate, Thane",
                "quantity": null,
                "unit_price": null,
                "amount": null
            },
            {
                "description": "WestThane, Maharashtra",
                "quantity": null,
                "unit_price": null,
                "amount": null
            },
            {
                "description": "India",
                "quantity": null,
                "unit_price": null,
                "amount": null
            },
            {
                "description": "Tel No.: +",
                "quantity": null,
                "unit_price": null,
                "amount": null
            },
            {
                "description": "GST No.:",
                "quantity": null,
                "unit_price": null,
                "amount": null
            },
            {
                "description": "Ship From",
                "quantity": null,
                "unit_price": null,
                "amount": null
            },
            {
                "description": "BRIGHT WH",
                "quantity": null,
                "unit_price": null,
                "amount": null
            },
            {
                "description": "Harihar Complex, Bldg. No. A",
                "quantity": null,
                "unit_price": null,
                "amount": null
            },
            {
                "description": "to",
                "quantity": null,
                "unit_price": null,
                "amount": null
            },
            {
                "description": "Near Mankoli Naka, Dapode Village",
                "quantity": null,
                "unit_price": null,
                "amount": null
            },
            {
                "description": "Bhiwandi, Thane,",
                "quantity": null,
                "unit_price": null,
                "amount": null
            },
            {
                "description": "India",
                "quantity": null,
                "unit_price": null,
                "amount": null
            },
            {
                "description": "GST No. -",
                "quantity": null,
                "unit_price": null,
                "amount": null
            },
            {
                "description": "GST Amount Incl.",
                "quantity": null,
                "unit_price": null,
                "amount": null
            },
            {
                "description": "GST % Amount GST (USD)",
                "quantity": null,
                "unit_price": null,
                "amount": null
            },
            {
                "description": "FORTY THREE THOUSAND FIVE HUNDRED FORTY",
                "quantity": null,
                "unit_price": null,
                "amount": null
            },
            {
                "description": "TWO DOLLAR AND ZERO CENTS US Dollar",
                "quantity": null,
                "unit_price": null,
                "amount": null
            },
            {
                "description": "invoice is issued for this sale.",
                "quantity": null,
                "unit_price": null,
                "amount": null
            },
            {
                "description": "*This is an electronically generated document, does not require any signature*",
                "quantity": null,
                "unit_price": null,
                "amount": null
            },
            {
                "description": "Page",
                "quantity": null,
                "unit_price": null,
                "amount": null
            },
            {
                "description": "Continued...",
                "quantity": null,
                "unit_price": null,
                "amount": null
            }
        ],
        "page_number": 1,
        "filename": "CORAPLUS INVOICE.pdf",
        "raw_text": "Tax Invoice\n\nInvoice No.: CS/PSI/101490\nInvoice Date: 05-August-2025\nInvoice Due Date: 03-November-2025\n\nBill To\n\nNiochem FZE\n\nPO Box: 262000, Jafza View 18,\nJebel Ali Free Zone,\n\nDubai\n\n26200\n\nUnited Arab Emirates\n\nTel No.: +971 (4) 345 5819\n\nSN Description\n\n1 LUBIMAX S 6321\nSoluble Cutting Oil Additive\n(Emulsifier)\nOrigin: India\nHS Code: 3811.21.00\nPacking: 80 DRM205KG of 205kg\nDrums on Pallet\n\nTotal\n\nPayment Terms: 90 Days After Invoice Date\nDelivery Terms: FOB\n\nPort of Loading: Nhava Sheva, India\n\nPort of Discharge : Jebel Ali, UAE\n\nP/I No.: CS/SO/101570\n\nP/| Date: 23/07/2025\n\nSales Order No.: CS/SO/101570\n\nSales Order Date: 23/07/2025\n\nTotal Taxable Value : INR 3,140,190.00\nTotal GST Value : INR 565,234.20\n\nTotal Invoice Value : INR 3,705,424.20\nExchange Rate : 85.10\nGNX : 200\n\nRemarks:\n\nUOM\nMT\n\nMT\n\nShip To\nNiochem FZE\n\nPO Box: 262000, Jafza View 18,\n\nJebel Ali Free Zone,\nDubai\n\n26200\n\nUnited Arab Emirates\n\nQty Unit Price\n16.400 2,250.00\n\n16.400 Total Amount Including GST in USD\n\nAmount\nExcl. GST\n\n36,900.00\n\n2\n\nCO coraptus\n\nCoraplus India Private Limited\nPlot No. A-13/1, Road No.22,MIDC,\nWagle Industrial Estate, Thane\nWestThane, Maharashtra\n\nIndia\n\nTel No.: +91 8879111244\n\nGST No.: 27AAHCE4277B1ZQ\n\nShip From\n\nBRIGHT WH\n\nHarihar Complex, Bldg. No. A10, Gala No.: 8\nto 11\n\nNear Mankoli Naka, Dapode Village\nBhiwandi, Thane, 421302\n\nIndia\n\nGST No. - 27AAHCE4277B1ZQ\n\nGST Amount Incl.\n\nGST % Amount GST (USD)\n18 6,642.00 43,542.00\n43,542.00\n\nFORTY THREE THOUSAND FIVE HUNDRED FORTY\nTWO DOLLAR AND ZERO CENTS US Dollar\n\n1. General Sales conditions are provided on the second page of this Commercial Invoice.\n2. The beneficiary certify that this Commercial invoice shows the actual price of the goods and Services as described above and no other\n\ninvoice is issued for this sale.\n\n3. We intend to claim Duty drawback and RoDTEP, if applicable for above HS code.\n\n*This is an electronically generated document, does not require any signature*\n\nPage 1/2\n\nContinued...\n",
        "_parsed_lines": [
            {
                "filename": "CORAPLUS INVOICE.pdf",
                "invoice_number": "",
                "invoice_date": "23/07/2025",
                "product_name": "1 LUBIMAX S 6321",
                "qty": 16.4,
                "qty_uom": "MT",
                "currency": "USD",
                "unit_price": 2250.0,
                "amount_usd": 36900.0,
                "confidence": 0.8,
                "raw_line": "16.400 2,250.00"
            },
            {
                "filename": "CORAPLUS INVOICE.pdf",
                "invoice_number": "",
                "invoice_date": "23/07/2025",
                "product_name": "1 LUBIMAX S 6321",
                "qty": 18.0,
                "qty_uom": "MT",
                "currency": "USD",
                "unit_price": 6642.0,
                "amount_usd": 119556.0,
                "confidence": 0.8,
                "raw_line": "18 6,642.00 43,542.00"
            }
        ],
        "_discarded_lines": [
            {
                "raw_line": "Date: 05-Aug-2025",
                "reason": "no_match"
            },
            {
                "raw_line": "Dubai,26200",
                "reason": "no_match"
            },
            {
                "raw_line": "Net Weight: 16,400 Kg",
                "reason": "no_match"
            },
            {
                "raw_line": "Gross Weight: 18,320 Kg",
                "reason": "no_match"
            },
            {
                "raw_line": "Total 16,400 Kg 18,320 Kg 16.40 MT 20 Pallet",
                "reason": "no_match"
            },
            {
                "raw_line": "Page 1 of 1",
                "reason": "no_match"
            }
        ]
    },
    {
        "invoice_number": "/Date",
        "date": "",
        "company": "Coraplus India Pvt. Ltd.",
        "amount": "16.40",
        "items": [],
        "page_number": 2,
        "filename": "CORAPLUS INVOICE.pdf",
        "raw_text": "PACKING LIST\n\nRef. No. CS/DO/101439\nDate: 05-Aug-2025\n\nBill To\n\nNiochem FZE\n\nPO Box: 262000, Jafza View 18,\nJebel Ali Free Zone,\nDubai,26200\n\nUnited Arab Emirates\n\nTel: +971 (4) 345 5819\n\nShip To\n\nSame as Bill To\n\nQ\n\nCToRAPLus\n\nA Vestcorp Holdings Company\n\nCoraplus India Pvt. Ltd.\nP.O. Box: 400093, Mumbai, India\nTel.: +91 (887) 911 1244\nWeb: www.coraplus.com\nGST: 27AAHCE4277B1ZQ\n\nNo. _ Description Lot No. Net Wt. Gross Wt. Panay Secondary\nack Pack\n1 LUBIMAX S 6321 16,400 Kg 18,320 Kg 16.40 MT 20 Pallet\n2207425079089 0 Kg 0 Kg 4.1 MT 5 Pallet\nOrigin: India 2207425089003 0 Kg 0 Kg 12.3 MT 15 Pallet\nHS Code: 3811.21.00\nNet Weight: 16,400 Kg\nGross Weight: 18,320 Kg\nPacking: 205kg Drums on Pallet\nTotal 16,400 Kg 18,320 Kg 16.40 MT 20 Pallet\n\nInvoice No./Date : CS/PSI/101490 / 05-Aug-2025\n\nClient PO No./Date : CS/SO/101570 - NIOCHEM FZE ICSO\n\nThis electronically generated document does not require a signature\n\nPage 1 of 1\n",
        "_parsed_lines": [
            {
                "filename": "CORAPLUS INVOICE.pdf",
                "invoice_number": "/Date",
                "invoice_date": "",
                "material_code": null,
                "hs_code": null,
                "qty": null,
                "qty_uom": null,
                "currency": null,
                "amount_detected": 439.0,
                "amount_inr": null,
                "amount_usd": null,
                "confidence": 0.4,
                "raw_line": "Ref. No. CS/DO/101439"
            },
            {
                "filename": "CORAPLUS INVOICE.pdf",
                "invoice_number": "/Date",
                "invoice_date": "",
                "material_code": null,
                "hs_code": null,
                "qty": null,
                "qty_uom": null,
                "currency": null,
                "amount_detected": 18.0,
                "amount_inr": null,
                "amount_usd": null,
                "confidence": 0.4,
                "raw_line": "PO Box: 262000, Jafza View 18,"
            },
            {
                "filename": "CORAPLUS INVOICE.pdf",
                "invoice_number": "/Date",
                "invoice_date": "",
                "material_code": "5819",
                "hs_code": null,
                "qty": null,
                "qty_uom": null,
                "currency": null,
                "amount_detected": 9.0,
                "amount_inr": null,
                "amount_usd": null,
                "confidence": 0.5,
                "raw_line": "Tel: +971 (4) 345 5819"
            },
            {
                "filename": "CORAPLUS INVOICE.pdf",
                "invoice_number": "/Date",
                "invoice_date": "",
                "material_code": null,
                "hs_code": null,
                "qty": null,
                "qty_uom": null,
                "currency": null,
                "amount_detected": 93.0,
                "amount_inr": null,
                "amount_usd": null,
                "confidence": 0.4,
                "raw_line": "P.O. Box: 400093, Mumbai, India"
            },
            {
                "filename": "CORAPLUS INVOICE.pdf",
                "invoice_number": "/Date",
                "invoice_date": "",
                "material_code": "1244",
                "hs_code": null,
                "qty": null,
                "qty_uom": null,
                "currency": null,
                "amount_detected": 4.0,
                "amount_inr": null,
                "amount_usd": null,
                "confidence": 0.5,
                "raw_line": "Tel.: +91 (887) 911 1244"
            },
            {
                "filename": "CORAPLUS INVOICE.pdf",
                "invoice_number": "/Date",
                "invoice_date": "",
                "material_code": "27AAHCE4277B1ZQ",
                "hs_code": null,
                "qty": null,
                "qty_uom": null,
                "currency": null,
                "amount_detected": 1.0,
                "amount_inr": null,
                "amount_usd": null,
                "confidence": 0.5,
                "raw_line": "GST: 27AAHCE4277B1ZQ"
            },
            {
                "filename": "CORAPLUS INVOICE.pdf",
                "invoice_number": "/Date",
                "invoice_date": "",
                "material_code": "6321",
                "hs_code": null,
                "qty": 16.4,
                "qty_uom": "MT",
                "currency": null,
                "amount_detected": 20.0,
                "amount_inr": null,
                "amount_usd": null,
                "confidence": 0.7,
                "raw_line": "1 LUBIMAX S 6321 16,400 Kg 18,320 Kg 16.40 MT 20 Pallet"
            },
            {
                "filename": "CORAPLUS INVOICE.pdf",
                "invoice_number": "/Date",
                "invoice_date": "",
                "material_code": "2207425079089",
                "hs_code": null,
                "qty": 0.0,
                "qty_uom": "Kg",
                "currency": null,
                "amount_detected": 5.0,
                "amount_inr": null,
                "amount_usd": null,
                "confidence": 0.5,
                "raw_line": "2207425079089 0 Kg 0 Kg 4.1 MT 5 Pallet"
            },
            {
                "filename": "CORAPLUS INVOICE.pdf",
                "invoice_number": "/Date",
                "invoice_date": "",
                "material_code": "2207425089003",
                "hs_code": null,
                "qty": 0.0,
                "qty_uom": "Kg",
                "currency": null,
                "amount_detected": 15.0,
                "amount_inr": null,
                "amount_usd": null,
                "confidence": 0.5,
                "raw_line": "Origin: India 2207425089003 0 Kg 0 Kg 12.3 MT 15 Pallet"
            },
            {
                "filename": "CORAPLUS INVOICE.pdf",
                "invoice_number": "/Date",
                "invoice_date": "",
                "material_code": null,
                "hs_code": null,
                "qty": null,
                "qty_uom": null,
                "currency": null,
                "amount_detected": 0.0,
                "amount_inr": null,
                "amount_usd": null,
                "confidence": 0.4,
                "raw_line": "HS Code: 3811.21.00"
            },
            {
                "filename": "CORAPLUS INVOICE.pdf",
                "invoice_number": "/Date",
                "invoice_date": "",
                "material_code": "205kg",
                "hs_code": null,
                "qty": null,
                "qty_uom": null,
                "currency": null,
                "amount_detected": 205.0,
                "amount_inr": null,
                "amount_usd": null,
                "confidence": 0.5,
                "raw_line": "Packing: 205kg Drums on Pallet"
            },
            {
                "filename": "CORAPLUS INVOICE.pdf",
                "invoice_number": "/Date",
                "invoice_date": "",
                "material_code": null,
                "hs_code": null,
                "qty": null,
                "qty_uom": null,
                "currency": null,
                "amount_detected": 5.0,
                "amount_inr": null,
                "amount_usd": null,
                "confidence": 0.4,
                "raw_line": "Invoice No./Date : CS/PSI/101490 / 05-Aug-2025"
            },
            {
                "filename": "CORAPLUS INVOICE.pdf",
                "invoice_number": "/Date",
                "invoice_date": "",
                "material_code": null,
                "hs_code": null,
                "qty": null,
                "qty_uom": null,
                "currency": null,
                "amount_detected": 570.0,
                "amount_inr": null,
                "amount_usd": null,
                "confidence": 0.4,
                "raw_line": "Client PO No./Date : CS/SO/101570 - NIOCHEM FZE ICSO"
            }
        ],
        "_discarded_lines": [
            {
                "raw_line": "Date: 05-Aug-2025",
                "reason": "no_match"
            },
            {
                "raw_line": "Dubai,26200",
                "reason": "no_match"
            },
            {
                "raw_line": "Net Weight: 16,400 Kg",
                "reason": "no_match"
            },
            {
                "raw_line": "Gross Weight: 18,320 Kg",
                "reason": "no_match"
            },
            {
                "raw_line": "Total 16,400 Kg 18,320 Kg 16.40 MT 20 Pallet",
                "reason": "no_match"
            },
            {
                "raw_line": "Page 1 of 1",
                "reason": "no_match"
            }
        ]
    }
]